LICENSE.txt
MANIFEST.in
readme.md
setup.py
page_elements/__init__.py
page_elements/checkbox.py
page_elements/decorators.py
page_elements/element.py
page_elements/input.py
page_elements/select_box.py
page_elements/textarea.py
selenium_page_elements.egg-info/PKG-INFO
selenium_page_elements.egg-info/SOURCES.txt
selenium_page_elements.egg-info/dependency_links.txt
selenium_page_elements.egg-info/requires.txt
selenium_page_elements.egg-info/top_level.txt