Metadata-Version: 1.1
Name: selenium-page-elements
Version: 0.1.4
Summary: A small library for simplifying page objects.
Home-page: https://github.com/jenterkin/selenium-page-elements
Author: Jordan Enterkin
Author-email: jordan.a.enterkin@gmail.com
License: MIT
Keywords: selenium page objects
Platform: UNKNOWN
Classifier: Development Status :: 3 - Alpha
Classifier: Intended Audience :: Developers
Classifier: Topic :: Software Development :: Libraries
Classifier: Topic :: Software Development :: Testing
Classifier: License :: OSI Approved :: MIT License
Classifier: Programming Language :: Python :: 3.6
